SigProfilerHotSpots/SigProfilerHotSpots.py
SigProfilerHotSpots/__init__.py
SigProfilerHotSpots/classifyFunctions.py
SigProfilerHotSpots/classifyFunctions_original_Feb5_2021.py
SigProfilerHotSpots/hotspot.py
SigProfilerHotSpots/plottingFunctions.py
SigProfilerHotSpots/version.py
SigProfilerHotSpots-0.0.28.dist-info/METADATA
SigProfilerHotSpots-0.0.28.dist-info/RECORD
SigProfilerHotSpots-0.0.28.dist-info/WHEEL
SigProfilerHotSpots-0.0.28.dist-info/top_level.txt
