Metadata-Version: 2.1
Name: SigProfilerHotSpots
Version: 0.0.28
Summary: SigProfilerHotSpots tool
Home-page: UNKNOWN
Author: Erik Bergstrom
Author-email: ebergstr@eng.ucsd.edu
License: UCSD
Platform: UNKNOWN
Requires-Dist: matplotlib (>=3.3.0)
Requires-Dist: sigProfilerPlotting (>=1.1.8)
Requires-Dist: SigProfilerMatrixGenerator (>=1.2.4)
Requires-Dist: SigProfilerSimulator (>=1.1.3)
Requires-Dist: statsmodels (>=0.9.0)
Requires-Dist: scipy (>=1.1.0)
Requires-Dist: pandas (>=0.23.4)
Requires-Dist: numpy (>=1.17.3)
Requires-Dist: SigProfilerExtractor (>=1.0.17)
